st_click_detector/__init__.py
st_click_detector/frontend/build/asset-manifest.json
st_click_detector/frontend/build/bootstrap.min.css
st_click_detector/frontend/build/index.html
st_click_detector/frontend/build/precache-manifest.13dab04760e158588e166a192ac6dce4.js
st_click_detector/frontend/build/precache-manifest.3b49fe6f7f5f5921cb199d776fbbad8d.js
st_click_detector/frontend/build/precache-manifest.466dcc66b6098aead2abda12f8ec767c.js
st_click_detector/frontend/build/precache-manifest.95c2c1e1f1654ebec9af9266d14804c1.js
st_click_detector/frontend/build/precache-manifest.c0c3a30b3204de71eae09b605221e5ca.js
st_click_detector/frontend/build/precache-manifest.d03e06f4df8395baae0ba37fde077bd1.js
st_click_detector/frontend/build/precache-manifest.ef65f96f76c9bd2797497df9384ec9b3.js
st_click_detector/frontend/build/service-worker.js
st_click_detector/frontend/build/static/js/2.04f38cb3.chunk.js
st_click_detector/frontend/build/static/js/2.04f38cb3.chunk.js.LICENSE.txt
st_click_detector/frontend/build/static/js/2.04f38cb3.chunk.js.map
st_click_detector/frontend/build/static/js/2.7524ebb4.chunk.js
st_click_detector/frontend/build/static/js/2.7524ebb4.chunk.js.LICENSE.txt
st_click_detector/frontend/build/static/js/2.7524ebb4.chunk.js.map
st_click_detector/frontend/build/static/js/2.eadf74be.chunk.js
st_click_detector/frontend/build/static/js/2.eadf74be.chunk.js.LICENSE.txt
st_click_detector/frontend/build/static/js/2.eadf74be.chunk.js.map
st_click_detector/frontend/build/static/js/main.3a09928b.chunk.js
st_click_detector/frontend/build/static/js/main.3a09928b.chunk.js.map
st_click_detector/frontend/build/static/js/main.8149145a.chunk.js
st_click_detector/frontend/build/static/js/main.8149145a.chunk.js.map
st_click_detector/frontend/build/static/js/main.924e8b5c.chunk.js
st_click_detector/frontend/build/static/js/main.924e8b5c.chunk.js.map
st_click_detector/frontend/build/static/js/main.a864f6c0.chunk.js
st_click_detector/frontend/build/static/js/main.a864f6c0.chunk.js.map
st_click_detector-0.1.2.dist-info/LICENSE
st_click_detector-0.1.2.dist-info/METADATA
st_click_detector-0.1.2.dist-info/WHEEL
st_click_detector-0.1.2.dist-info/top_level.txt
st_click_detector-0.1.2.dist-info/RECORD
