Metadata-Version: 2.1
Name: st-click-detector
Version: 0.1.2
Summary: A Streamlit component to detect clicks
Home-page: UNKNOWN
Author: 
Author-email: 
License: UNKNOWN
Platform: UNKNOWN
Requires-Python: >=3.6
License-File: LICENSE
Requires-Dist: streamlit (>=0.63)
